{"versions": ["67.0b8", "67.0b7", "67.0b6", "67.0b9", "67.0b4", "67.0b3", "67.0b5"], "start_date": "2019-03-31", "end_date": "2019-04-10", "signatures": {"_invalid_parameter": {"tc_rank": 110, "crash_count": 6, "startup_percent": 1.0, "bugs": [{"resolution": "FIXED", "cf_status_firefox67": "---", "id": 1271131, "cf_tracking_firefox67": "---", "cf_status_firefox68": "---", "last_change_time": "2016-05-10T10:17:51Z"}, {"resolution": "FIXED", "id": 1216951, "last_change_time": "2019-02-13T16:50:42Z"}], "estimated_user_count": 1}, "js::jit::MConstant::New": {"tc_rank": 140, "crash_count": 5, "startup_percent": 1.0, "bugs": [{"resolution": "INCOMPLETE", "cf_status_firefox67": "---", "id": 1072782, "cf_tracking_firefox67": "---", "cf_status_firefox68": "---", "last_change_time": "2014-10-27T10:00:17Z"}], "estimated_user_count": 2}, "js::ScriptSourceObject::initFromOptions": {"tc_rank": 141, "crash_count": 5, "startup_percent": 1.0, "bugs": [{"resolution": "FIXED", "cf_status_firefox67": "---", "id": 1035287, "cf_tracking_firefox67": "---", "cf_status_firefox68": "---", "last_change_time": "2018-07-20T19:38:38Z"}, {"resolution": "FIXED", "cf_status_firefox67": "---", "id": 1037666, "cf_tracking_firefox67": "---", "cf_status_firefox68": "---", "last_change_time": "2016-06-04T23:01:03Z"}, {"resolution": "", "cf_status_firefox67": "---", "id": 1166626, "cf_tracking_firefox67": "---", "cf_status_firefox68": "---", "last_change_time": "2015-10-13T14:40:17Z"}], "estimated_user_count": 1}, "memmove | sqlite3RunParser": {"tc_rank": 111, "crash_count": 6, "startup_percent": 1.0, "bugs": [], "estimated_user_count": 1}, "js::frontend::TokenStreamSpecific<T>::regexpLiteral": {"tc_rank": 153, "crash_count": 5, "startup_percent": 1.0, "bugs": [], "estimated_user_count": 1}, "mozilla::layers::ShadowLayerForwarder::ReleaseCompositable": {"tc_rank": 91, "crash_count": 7, "startup_percent": 1.0, "bugs": [], "estimated_user_count": 1}, "JSObject::is<T>": {"tc_rank": 56, "crash_count": 9, "startup_percent": 1.0, "bugs": [{"resolution": "", "cf_status_firefox67": "---", "id": 977168, "cf_tracking_firefox67": "---", "cf_status_firefox68": "---", "last_change_time": "2015-10-13T14:35:06Z"}, {"resolution": "INCOMPLETE", "cf_status_firefox67": "---", "id": 1320559, "cf_tracking_firefox67": "---", "cf_status_firefox68": "---", "last_change_time": "2017-01-16T09:29:56Z"}], "estimated_user_count": 1}, "mozilla::widget::GfxInfoBase::FindBlocklistedDeviceInList": {"tc_rank": 143, "crash_count": 5, "startup_percent": 1.0, "bugs": [], "estimated_user_count": 1}, "mozilla::extensions::MatchGlob::Constructor": {"tc_rank": 71, "crash_count": 8, "startup_percent": 1.0, "bugs": [], "estimated_user_count": 1}, "mozilla::ScriptPreloader::NoteScript": {"tc_rank": 144, "crash_count": 5, "startup_percent": 1.0, "bugs": [], "estimated_user_count": 1}, "PLDHashTable::Iterator::Iterator | mozilla::dom::ImageTracker::SetLockingState": {"tc_rank": 43, "crash_count": 11, "startup_percent": 1.0, "bugs": [], "estimated_user_count": 1}, "js::ValueToIterator": {"tc_rank": 46, "crash_count": 10, "startup_percent": 1.0, "bugs": [], "estimated_user_count": 1}, "insertCell": {"tc_rank": 92, "crash_count": 7, "startup_percent": 1.0, "bugs": [{"resolution": "WORKSFORME", "cf_status_firefox67": "---", "id": 612089, "cf_tracking_firefox67": "---", "cf_status_firefox68": "---", "last_change_time": "2011-12-08T03:31:06Z"}], "estimated_user_count": 1}, "OOM | small": {"tc_rank": 3, "crash_count": 72, "startup_percent": 1.0, "bugs": [{"resolution": "", "cf_status_firefox67": "---", "id": 683271, "cf_tracking_firefox67": "---", "cf_status_firefox68": "---", "last_change_time": "2018-12-13T11:46:00Z"}, {"resolution": "WORKSFORME", "id": 1028720, "last_change_time": "2016-11-14T22:46:38Z"}, {"resolution": "WONTFIX", "cf_status_firefox67": "---", "id": 1034254, "cf_tracking_firefox67": "---", "cf_status_firefox68": "---", "last_change_time": "2016-08-24T19:54:55Z"}, {"resolution": "WORKSFORME", "cf_status_firefox67": "---", "id": 1048619, "cf_tracking_firefox67": "---", "cf_status_firefox68": "---", "last_change_time": "2016-07-31T18:00:39Z"}, {"resolution": "FIXED", "cf_status_firefox67": "---", "id": 1053934, "cf_tracking_firefox67": "---", "cf_status_firefox68": "---", "last_change_time": "2015-05-27T03:59:01Z"}, {"resolution": "INCOMPLETE", "cf_status_firefox67": "---", "id": 1057869, "cf_tracking_firefox67": "---", "cf_status_firefox68": "---", "last_change_time": "2015-04-13T14:49:28Z"}, {"resolution": "WORKSFORME", "cf_status_firefox67": "---", "id": 1059563, "cf_tracking_firefox67": "---", "cf_status_firefox68": "---", "last_change_time": "2018-01-16T21:31:43Z"}, {"resolution": "", "cf_status_firefox67": "---", "id": 1060268, "cf_tracking_firefox67": "---", "cf_status_firefox68": "---", "last_change_time": "2017-09-21T22:10:11Z"}, {"resolution": "", "cf_status_firefox67": "---", "id": 1066036, "cf_tracking_firefox67": "---", "cf_status_firefox68": "---", "last_change_time": "2017-09-14T00:12:21Z"}, {"resolution": "FIXED", "cf_status_firefox67": "---", "id": 1081790, "cf_tracking_firefox67": "---", "cf_status_firefox68": "---", "last_change_time": "2014-12-19T19:24:38Z"}, {"resolution": "", "cf_status_firefox67": "---", "id": 1089682, "cf_tracking_firefox67": "---", "cf_status_firefox68": "---", "last_change_time": "2017-03-04T17:02:01Z"}, {"resolution": "WORKSFORME", "cf_status_firefox67": "---", "id": 1115929, "cf_tracking_firefox67": "---", "cf_status_firefox68": "---", "last_change_time": "2016-07-19T16:18:49Z"}, {"resolution": "FIXED", "cf_status_firefox67": "---", "id": 1127554, "cf_tracking_firefox67": "---", "cf_status_firefox68": "---", "last_change_time": "2015-02-22T01:02:16Z"}, {"resolution": "WORKSFORME", "cf_status_firefox67": "---", "id": 1153515, "cf_tracking_firefox67": "---", "cf_status_firefox68": "---", "last_change_time": "2017-02-17T11:48:19Z"}, {"resolution": "WORKSFORME", "id": 1174324, "last_change_time": "2016-07-31T16:41:38Z"}, {"resolution": "", "cf_status_firefox67": "---", "id": 1205110, "cf_tracking_firefox67": "---", "cf_status_firefox68": "---", "last_change_time": "2019-02-11T20:44:59Z"}, {"resolution": "WORKSFORME", "cf_status_firefox67": "---", "id": 1205771, "cf_tracking_firefox67": "---", "cf_status_firefox68": "---", "last_change_time": "2015-12-31T15:22:18Z"}, {"resolution": "WORKSFORME", "cf_status_firefox67": "---", "id": 1209673, "cf_tracking_firefox67": "---", "cf_status_firefox68": "---", "last_change_time": "2016-05-27T22:45:49Z"}, {"resolution": "WORKSFORME", "cf_status_firefox67": "---", "id": 1215181, "cf_tracking_firefox67": "---", "cf_status_firefox68": "---", "last_change_time": "2016-02-13T20:28:02Z"}, {"resolution": "", "cf_status_firefox67": "---", "id": 1234842, "cf_tracking_firefox67": "---", "cf_status_firefox68": "---", "last_change_time": "2018-08-08T17:06:02Z"}, {"resolution": "", "cf_status_firefox67": "---", "id": 1310134, "cf_tracking_firefox67": "---", "cf_status_firefox68": "---", "last_change_time": "2018-02-08T01:48:21Z"}, {"resolution": "", "cf_status_firefox67": "---", "id": 1316798, "cf_tracking_firefox67": "---", "cf_status_firefox68": "---", "last_change_time": "2018-11-02T14:28:40Z"}, {"resolution": "", "cf_status_firefox67": "---", "id": 1318272, "cf_tracking_firefox67": "---", "cf_status_firefox68": "---", "last_change_time": "2018-11-05T12:58:03Z"}, {"resolution": "FIXED", "cf_status_firefox67": "---", "id": 1333070, "cf_tracking_firefox67": "---", "cf_status_firefox68": "---", "last_change_time": "2017-09-20T08:40:37Z"}, {"resolution": "WORKSFORME", "cf_status_firefox67": "---", "id": 1341573, "cf_tracking_firefox67": "---", "cf_status_firefox68": "---", "last_change_time": "2017-02-23T11:25:59Z"}, {"resolution": "INCOMPLETE", "cf_status_firefox67": "---", "id": 1341744, "cf_tracking_firefox67": "---", "cf_status_firefox68": "---", "last_change_time": "2017-10-11T19:59:55Z"}, {"resolution": "", "cf_status_firefox67": "---", "id": 1342017, "cf_tracking_firefox67": "---", "cf_status_firefox68": "---", "last_change_time": "2018-02-08T01:48:32Z"}, {"resolution": "FIXED", "cf_status_firefox67": "---", "id": 1353762, "cf_tracking_firefox67": "---", "cf_status_firefox68": "---", "last_change_time": "2017-09-01T08:55:36Z"}, {"resolution": "", "cf_status_firefox67": "---", "id": 1357359, "cf_tracking_firefox67": "---", "cf_status_firefox68": "---", "last_change_time": "2018-01-24T11:51:04Z"}, {"resolution": "INVALID", "cf_status_firefox67": "---", "id": 1361354, "cf_tracking_firefox67": "---", "cf_status_firefox68": "---", "last_change_time": "2017-09-20T09:42:09Z"}, {"resolution": "FIXED", "cf_status_firefox67": "---", "id": 1384026, "cf_tracking_firefox67": "---", "cf_status_firefox68": "---", "last_change_time": "2017-07-27T01:06:00Z"}, {"resolution": "INCOMPLETE", "cf_status_firefox67": "---", "id": 1409986, "cf_tracking_firefox67": "---", "cf_status_firefox68": "---", "last_change_time": "2017-10-20T04:28:14Z"}, {"resolution": "", "cf_status_firefox67": "---", "id": 1421345, "cf_tracking_firefox67": "---", "cf_status_firefox68": "---", "last_change_time": "2019-03-21T08:41:44Z"}, {"resolution": "FIXED", "cf_status_firefox67": "---", "id": 1428612, "cf_tracking_firefox67": "---", "cf_status_firefox68": "---", "last_change_time": "2018-01-31T23:26:11Z"}, {"resolution": "", "cf_status_firefox67": "---", "id": 1433816, "cf_tracking_firefox67": "---", "cf_status_firefox68": "---", "last_change_time": "2018-01-29T23:04:51Z"}, {"resolution": "WORKSFORME", "cf_status_firefox67": "---", "id": 1442965, "cf_tracking_firefox67": "---", "cf_status_firefox68": "---", "last_change_time": "2018-05-07T19:35:40Z"}, {"resolution": "", "cf_status_firefox67": "---", "id": 1458221, "cf_tracking_firefox67": "---", "cf_status_firefox68": "---", "last_change_time": "2018-12-13T11:45:58Z"}, {"resolution": "", "id": 1477582, "last_change_time": "2018-12-13T11:45:57Z"}, {"resolution": "FIXED", "cf_status_firefox67": "---", "id": 1505094, "cf_tracking_firefox67": "---", "cf_status_firefox68": "---", "last_change_time": "2018-12-27T00:56:14Z"}, {"resolution": "", "cf_status_firefox67": "affected", "id": 1519123, "cf_tracking_firefox67": "+", "cf_status_firefox68": "affected", "last_change_time": "2019-04-09T13:29:32Z"}, {"resolution": "INCOMPLETE", "cf_status_firefox67": "---", "id": 1519129, "cf_tracking_firefox67": "---", "cf_status_firefox68": "---", "last_change_time": "2019-01-31T20:40:29Z"}, {"resolution": "", "cf_status_firefox67": "affected", "id": 1541092, "cf_tracking_firefox67": "---", "cf_status_firefox68": "affected", "last_change_time": "2019-04-10T15:47:51Z"}, {"resolution": "FIXED", "cf_status_firefox67": "---", "id": 1190258, "cf_tracking_firefox67": "---", "cf_status_firefox68": "---", "last_change_time": "2015-08-09T22:18:42Z"}, {"resolution": "FIXED", "cf_status_firefox67": "---", "id": 1203973, "cf_tracking_firefox67": "---", "cf_status_firefox68": "---", "last_change_time": "2016-03-03T14:30:54Z"}], "estimated_user_count": 47}, "mozilla::PresShell::Destroy": {"tc_rank": 145, "crash_count": 5, "startup_percent": 1.0, "bugs": [], "estimated_user_count": 1}, "js::frontend::GeneralParser<T>::tryStatement": {"tc_rank": 112, "crash_count": 6, "startup_percent": 1.0, "bugs": [], "estimated_user_count": 1}, "udata_openChoice_63": {"tc_rank": 72, "crash_count": 8, "startup_percent": 1.0, "bugs": [], "estimated_user_count": 1}, "nsWindow::SetNonClientMargins": {"tc_rank": 146, "crash_count": 5, "startup_percent": 1.0, "bugs": [], "estimated_user_count": 1}, "nsCategoryManager::Create": {"tc_rank": 147, "crash_count": 5, "startup_percent": 1.0, "bugs": [], "estimated_user_count": 1}, "js::obj_create": {"tc_rank": 93, "crash_count": 7, "startup_percent": 1.0, "bugs": [], "estimated_user_count": 1}, "ComputeCrc32": {"tc_rank": 16, "crash_count": 19, "startup_percent": 1.0, "bugs": [{"resolution": "", "cf_status_firefox67": "---", "id": 1407741, "cf_tracking_firefox67": "---", "cf_status_firefox68": "---", "last_change_time": "2017-10-13T15:42:05Z"}, {"resolution": "", "cf_status_firefox67": "---", "id": 1485425, "cf_tracking_firefox67": "---", "cf_status_firefox68": "---", "last_change_time": "2018-11-12T22:23:13Z"}], "estimated_user_count": 3}, "js::AtomizeChars<T>": {"tc_rank": 30, "crash_count": 14, "startup_percent": 1.0, "bugs": [{"resolution": "FIXED", "cf_status_firefox67": "---", "id": 1373934, "cf_tracking_firefox67": "---", "cf_status_firefox68": "---", "last_change_time": "2018-08-29T05:56:33Z"}, {"resolution": "", "cf_status_firefox67": "---", "id": 1444442, "cf_tracking_firefox67": "---", "cf_status_firefox68": "---", "last_change_time": "2018-05-16T22:26:27Z"}], "estimated_user_count": 6}, "mozilla::net::ExtensionProtocolHandler::GetSingleton": {"tc_rank": 148, "crash_count": 5, "startup_percent": 1.0, "bugs": [], "estimated_user_count": 1}, "memcpy | mozilla::dom::ipc::WritableSharedMap::Serialize": {"tc_rank": 149, "crash_count": 5, "startup_percent": 1.0, "bugs": [], "estimated_user_count": 1}, "CThreadInputMgr::_CleanupContexts": {"tc_rank": 113, "crash_count": 6, "startup_percent": 1.0, "bugs": [], "estimated_user_count": 1}, "JSAutoNullableRealm::~JSAutoNullableRealm": {"tc_rank": 114, "crash_count": 6, "startup_percent": 1.0, "bugs": [], "estimated_user_count": 1}, "mozilla::dom::binding_detail::GenericGetter<T>": {"tc_rank": 73, "crash_count": 8, "startup_percent": 1.0, "bugs": [], "estimated_user_count": 1}, "nsIPresShell::EnsureStyleFlush": {"tc_rank": 150, "crash_count": 5, "startup_percent": 1.0, "bugs": [], "estimated_user_count": 1}, "res_init": {"tc_rank": 115, "crash_count": 6, "startup_percent": 1.0, "bugs": [], "estimated_user_count": 1}, "iRectRelation": {"tc_rank": 151, "crash_count": 5, "startup_percent": 1.0, "bugs": [], "estimated_user_count": 1}, "EnumerateNativeProperties": {"tc_rank": 152, "crash_count": 5, "startup_percent": 1.0, "bugs": [{"resolution": "FIXED", "cf_status_firefox67": "---", "id": 851806, "cf_tracking_firefox67": "---", "cf_status_firefox68": "---", "last_change_time": "2016-02-09T17:25:05Z"}, {"resolution": "", "cf_status_firefox67": "---", "id": 1246987, "cf_tracking_firefox67": "---", "cf_status_firefox68": "---", "last_change_time": "2019-01-07T11:11:36Z"}], "estimated_user_count": 1}, "SetMenuItemBitmaps": {"tc_rank": 94, "crash_count": 7, "startup_percent": 1.0, "bugs": [], "estimated_user_count": 1}, "mozurl::mozurl_new": {"tc_rank": 142, "crash_count": 5, "startup_percent": 1.0, "bugs": [], "estimated_user_count": 1}, "`anonymous namespace'::EventListenerManagerHashInitEntry": {"tc_rank": 154, "crash_count": 5, "startup_percent": 1.0, "bugs": [], "estimated_user_count": 2}, "nsXPTCStubBase::Stub7": {"tc_rank": 116, "crash_count": 6, "startup_percent": 1.0, "bugs": [], "estimated_user_count": 1}, "js::frontend::GeneralParser<T>::innerFunction": {"tc_rank": 117, "crash_count": 6, "startup_percent": 1.0, "bugs": [], "estimated_user_count": 1}, "mozilla::dom::Document::SetReadyStateInternal": {"tc_rank": 155, "crash_count": 5, "startup_percent": 1.0, "bugs": [], "estimated_user_count": 1}, "mozilla::ipc::PInProcessChild::DestroySubtree": {"tc_rank": 156, "crash_count": 5, "startup_percent": 1.0, "bugs": [], "estimated_user_count": 1}, "u_setMemoryFunctions_63": {"tc_rank": 27, "crash_count": 15, "startup_percent": 1.0, "bugs": [], "estimated_user_count": 1}, "js::XDRScript<T>": {"tc_rank": 95, "crash_count": 7, "startup_percent": 1.0, "bugs": [{"resolution": "INVALID", "cf_status_firefox67": "---", "id": 790047, "cf_tracking_firefox67": "---", "cf_status_firefox68": "---", "last_change_time": "2018-03-09T17:13:22Z"}, {"resolution": "", "cf_status_firefox67": "---", "id": 1444442, "cf_tracking_firefox67": "---", "cf_status_firefox68": "---", "last_change_time": "2018-05-16T22:26:27Z"}], "estimated_user_count": 5}, "js::jit::BaselineCompiler::emitBody": {"tc_rank": 118, "crash_count": 6, "startup_percent": 1.0, "bugs": [{"resolution": "", "cf_status_firefox67": "---", "id": 1011732, "cf_tracking_firefox67": "---", "cf_status_firefox68": "---", "last_change_time": "2016-08-01T07:32:16Z"}, {"resolution": "FIXED", "cf_status_firefox67": "---", "id": 1109328, "cf_tracking_firefox67": "---", "cf_status_firefox68": "---", "last_change_time": "2014-12-23T17:58:17Z"}], "estimated_user_count": 2}, "js::ObjectGroup::callingAllocationSiteGroup": {"tc_rank": 57, "crash_count": 9, "startup_percent": 1.0, "bugs": [], "estimated_user_count": 2}, "js::ScriptSource::XDR<T>": {"tc_rank": 119, "crash_count": 6, "startup_percent": 1.0, "bugs": [], "estimated_user_count": 1}, "nsAtomSubTable::Search": {"tc_rank": 58, "crash_count": 9, "startup_percent": 1.0, "bugs": [], "estimated_user_count": 1}, "mozilla::dom::exceptions::CreateStack": {"tc_rank": 158, "crash_count": 5, "startup_percent": 1.0, "bugs": [], "estimated_user_count": 1}, "js::frontend::GeneralParser<T>::forStatement": {"tc_rank": 159, "crash_count": 5, "startup_percent": 1.0, "bugs": [], "estimated_user_count": 1}, "js::frontend::NameOpEmitter::emitAssignment": {"tc_rank": 160, "crash_count": 5, "startup_percent": 1.0, "bugs": [{"resolution": "", "cf_status_firefox67": "fix-optional", "id": 1524257, "cf_tracking_firefox67": "---", "cf_status_firefox68": "fix-optional", "last_change_time": "2019-04-10T09:02:18Z"}], "estimated_user_count": 1}, "mozilla::dom::DOMProxyHandler::EnsureExpandoObject": {"tc_rank": 120, "crash_count": 6, "startup_percent": 1.0, "bugs": [{"resolution": "FIXED", "cf_status_firefox67": "---", "id": 876080, "cf_tracking_firefox67": "---", "cf_status_firefox68": "---", "last_change_time": "2019-03-13T13:42:05Z"}, {"resolution": "", "cf_status_firefox67": "---", "id": 949893, "cf_tracking_firefox67": "---", "cf_status_firefox68": "---", "last_change_time": "2019-03-13T13:42:05Z"}], "estimated_user_count": 1}, "js::frontend::GeneralParser<T>::declarationName": {"tc_rank": 121, "crash_count": 6, "startup_percent": 1.0, "bugs": [], "estimated_user_count": 2}, "RefPtr<T>::~RefPtr | mozilla::dom::ipc::StructuredCloneData::~StructuredCloneData": {"tc_rank": 15, "crash_count": 20, "startup_percent": 1.0, "bugs": [], "estimated_user_count": 1}, "mozilla::dom::Document::DisconnectNodeTree": {"tc_rank": 59, "crash_count": 9, "startup_percent": 1.0, "bugs": [], "estimated_user_count": 1}, "GetUnclonedValue": {"tc_rank": 96, "crash_count": 7, "startup_percent": 1.0, "bugs": [], "estimated_user_count": 3}, "js::jit::ControlFlowGenerator::snoopControlFlow": {"tc_rank": 161, "crash_count": 5, "startup_percent": 1.0, "bugs": [{"resolution": "FIXED", "cf_status_firefox67": "---", "id": 1441012, "cf_tracking_firefox67": "---", "cf_status_firefox68": "---", "last_change_time": "2018-03-12T13:55:38Z"}], "estimated_user_count": 1}, "mozilla::RestyleManager::DoProcessPendingRestyles": {"tc_rank": 33, "crash_count": 13, "startup_percent": 1.0, "bugs": [], "estimated_user_count": 2}, "nsDocShell::InternalLoad": {"tc_rank": 74, "crash_count": 8, "startup_percent": 1.0, "bugs": [{"resolution": "FIXED", "cf_status_firefox67": "---", "id": 135868, "cf_tracking_firefox67": "---", "cf_status_firefox68": "---", "last_change_time": "2011-06-13T17:01:40Z"}, {"resolution": "FIXED", "cf_status_firefox67": "---", "id": 173308, "cf_tracking_firefox67": "---", "cf_status_firefox68": "---", "last_change_time": "2003-06-20T18:12:41Z"}, {"resolution": "FIXED", "cf_status_firefox67": "---", "id": 267249, "cf_tracking_firefox67": "---", "cf_status_firefox68": "---", "last_change_time": "2006-03-13T02:07:53Z"}, {"resolution": "WORKSFORME", "cf_status_firefox67": "---", "id": 443655, "cf_tracking_firefox67": "---", "cf_status_firefox68": "---", "last_change_time": "2017-10-19T02:10:31Z"}, {"resolution": "", "cf_status_firefox67": "---", "id": 854864, "cf_tracking_firefox67": "---", "cf_status_firefox68": "---", "last_change_time": "2016-11-03T10:39:59Z"}, {"resolution": "FIXED", "cf_status_firefox67": "---", "id": 1341657, "cf_tracking_firefox67": "---", "cf_status_firefox68": "---", "last_change_time": "2017-03-08T09:15:51Z"}], "estimated_user_count": 1}, "nsContentUtils::Init": {"tc_rank": 75, "crash_count": 8, "startup_percent": 1.0, "bugs": [{"resolution": "WORKSFORME", "cf_status_firefox67": "---", "id": 313232, "cf_tracking_firefox67": "---", "cf_status_firefox68": "---", "last_change_time": "2019-03-13T13:42:05Z"}], "estimated_user_count": 1}, "walIndexTryHdr": {"tc_rank": 44, "crash_count": 11, "startup_percent": 1.0, "bugs": [{"resolution": "", "cf_status_firefox67": "---", "id": 771138, "cf_tracking_firefox67": "---", "cf_status_firefox68": "---", "last_change_time": "2018-12-13T00:13:48Z"}], "estimated_user_count": 9}, "xul.dll | js::jit::JitRuntime::initialize": {"tc_rank": 60, "crash_count": 9, "startup_percent": 1.0, "bugs": [], "estimated_user_count": 1}, "array_isArray": {"tc_rank": 122, "crash_count": 6, "startup_percent": 1.0, "bugs": [], "estimated_user_count": 1}, "gfxPlatform::Init::<T>::__invoke | gfxPrefs::Pref::SetChangeCallback": {"tc_rank": 97, "crash_count": 7, "startup_percent": 1.0, "bugs": [], "estimated_user_count": 1}, "CreateModule<T>": {"tc_rank": 61, "crash_count": 9, "startup_percent": 1.0, "bugs": [], "estimated_user_count": 1}, "xpc::CreateSandboxObject": {"tc_rank": 62, "crash_count": 9, "startup_percent": 1.0, "bugs": [], "estimated_user_count": 1}, "mozilla::detail::HashTable<T>::changeTableSize | mozilla::detail::HashTable<T>::add<T> | js::SavedStacks::getLocation": {"tc_rank": 162, "crash_count": 5, "startup_percent": 1.0, "bugs": [], "estimated_user_count": 1}, "igd10iumd32.dll | nvumdshim.dll | NDXGI::CDevice::Present": {"tc_rank": 163, "crash_count": 5, "startup_percent": 1.0, "bugs": [], "estimated_user_count": 3}, "GetSpecialSystemDirectory": {"tc_rank": 76, "crash_count": 8, "startup_percent": 1.0, "bugs": [], "estimated_user_count": 1}, "@0x0 | trunc | PR_AttachThread | mozilla::storage::Connection::Close": {"tc_rank": 98, "crash_count": 7, "startup_percent": 1.0, "bugs": [], "estimated_user_count": 1}, "nsComponentManagerImpl::GetServiceLocked(class `anonymous namespace'::MutexLock& const, class `anonymous namespace'::EntryWrapper& const, const struct nsID& const, void**)": {"tc_rank": 34, "crash_count": 13, "startup_percent": 1.0, "bugs": [], "estimated_user_count": 3}, "js::frontend::ObjectEmitter::ObjectEmitter": {"tc_rank": 18, "crash_count": 18, "startup_percent": 1.0, "bugs": [], "estimated_user_count": 2}, "mozilla::dom::ChromeUtils_Binding::generateQI": {"tc_rank": 123, "crash_count": 6, "startup_percent": 1.0, "bugs": [], "estimated_user_count": 1}, "sqlite3Select": {"tc_rank": 19, "crash_count": 18, "startup_percent": 1.0, "bugs": [], "estimated_user_count": 1}, "js::GlobalObject::addIntrinsicValue": {"tc_rank": 99, "crash_count": 7, "startup_percent": 1.0, "bugs": [], "estimated_user_count": 1}, "nsGlobalWindowInner::nsGlobalWindowInner": {"tc_rank": 31, "crash_count": 14, "startup_percent": 1.0, "bugs": [], "estimated_user_count": 2}, "nsTSubstring<T>::AppendASCII": {"tc_rank": 124, "crash_count": 6, "startup_percent": 1.0, "bugs": [], "estimated_user_count": 0}, "mozilla::layers::EnsureLayerTreeMapReady": {"tc_rank": 164, "crash_count": 5, "startup_percent": 1.0, "bugs": [], "estimated_user_count": 1}, "yy_reduce": {"tc_rank": 28, "crash_count": 15, "startup_percent": 1.0, "bugs": [{"resolution": "", "cf_status_firefox67": "---", "id": 612266, "cf_tracking_firefox67": "---", "cf_status_firefox68": "---", "last_change_time": "2016-11-04T21:37:59Z"}], "estimated_user_count": 5}, "mozilla::dom::`anonymous namespace'::ClaimOnMainThread": {"tc_rank": 63, "crash_count": 9, "startup_percent": 1.0, "bugs": [], "estimated_user_count": 1}, "BaseAllocator::free | je_free | sqlite3_str_vappendf": {"tc_rank": 165, "crash_count": 5, "startup_percent": 1.0, "bugs": [], "estimated_user_count": 1}, "BaselineCacheIRCompiler::emitGuardGroup": {"tc_rank": 38, "crash_count": 12, "startup_percent": 1.0, "bugs": [], "estimated_user_count": 1}, "mozilla::Vector<T>::growStorageBy": {"tc_rank": 64, "crash_count": 9, "startup_percent": 1.0, "bugs": [{"resolution": "", "cf_status_firefox67": "---", "id": 1455595, "cf_tracking_firefox67": "---", "cf_status_firefox68": "---", "last_change_time": "2018-04-30T20:23:00Z"}], "estimated_user_count": 4}, "gfxPrefs::PrefTemplate<T>::PrefTemplate": {"tc_rank": 14, "crash_count": 21, "startup_percent": 1.0, "bugs": [], "estimated_user_count": 4}, "RtlAllocateHeap | GlobalAlloc": {"tc_rank": 45, "crash_count": 11, "startup_percent": 1.0, "bugs": [], "estimated_user_count": 1}, "js::jit::CacheIRCompiler::emitGuardSpecificInt32Immediate": {"tc_rank": 47, "crash_count": 10, "startup_percent": 1.0, "bugs": [], "estimated_user_count": 1}, "mozilla::dom::WebCryptoThreadPool::DispatchInternal": {"tc_rank": 166, "crash_count": 5, "startup_percent": 1.0, "bugs": [], "estimated_user_count": 1}, "cssparser::parser::Parser::next_including_whitespace_and_comments": {"tc_rank": 168, "crash_count": 5, "startup_percent": 1.0, "bugs": [{"resolution": "INCOMPLETE", "cf_status_firefox67": "---", "id": 1461870, "cf_tracking_firefox67": "---", "cf_status_firefox68": "---", "last_change_time": "2018-06-11T23:41:31Z"}], "estimated_user_count": 1}, "mozilla::detail::log_print": {"tc_rank": 169, "crash_count": 5, "startup_percent": 1.0, "bugs": [], "estimated_user_count": 1}, "nsInputStreamReadyEvent::QueryInterface": {"tc_rank": 170, "crash_count": 5, "startup_percent": 1.0, "bugs": [], "estimated_user_count": 1}, "std::basic_string<T>::_Copy": {"tc_rank": 100, "crash_count": 7, "startup_percent": 1.0, "bugs": [], "estimated_user_count": 2}, "mozilla::TokenizerBase<T>::Parse": {"tc_rank": 77, "crash_count": 8, "startup_percent": 1.0, "bugs": [], "estimated_user_count": 1}, "gfxPrefs::PrefTemplate<T>::Register": {"tc_rank": 78, "crash_count": 8, "startup_percent": 1.0, "bugs": [], "estimated_user_count": 1}, "nsChromeProtocolHandler::NewURI": {"tc_rank": 157, "crash_count": 5, "startup_percent": 1.0, "bugs": [], "estimated_user_count": 1}, "XPCWrappedNativeProto::GetNewOrUsed": {"tc_rank": 48, "crash_count": 10, "startup_percent": 1.0, "bugs": [], "estimated_user_count": 1}, "js::gcstats::Statistics::beginPhase": {"tc_rank": 35, "crash_count": 13, "startup_percent": 1.0, "bugs": [], "estimated_user_count": 2}, "js::frontend::RewritingParseNodeVisitor<T>::visit": {"tc_rank": 171, "crash_count": 5, "startup_percent": 1.0, "bugs": [], "estimated_user_count": 5}, "js::proxy": {"tc_rank": 125, "crash_count": 6, "startup_percent": 1.0, "bugs": [], "estimated_user_count": 2}, "klsihk64.dll | js::gc::GCRuntime::GCRuntime": {"tc_rank": 12, "crash_count": 23, "startup_percent": 1.0, "bugs": [], "estimated_user_count": 8}, "nsCOMArray_base::Clear": {"tc_rank": 32, "crash_count": 14, "startup_percent": 1.0, "bugs": [{"resolution": "", "id": 1454170, "last_change_time": "2019-03-30T11:08:23Z"}, {"resolution": "", "id": 1539028, "last_change_time": "2019-03-26T11:14:46Z"}], "estimated_user_count": 5}, "nsGlobalWindowOuter::Create": {"tc_rank": 172, "crash_count": 5, "startup_percent": 1.0, "bugs": [], "estimated_user_count": 1}, "mozilla::net::nsStandardURL::TemplatedMutator<T>::SetFile": {"tc_rank": 65, "crash_count": 9, "startup_percent": 1.0, "bugs": [], "estimated_user_count": 1}, "mozilla::dom::ContentProcessMessageManager_Binding::Wrap<T>": {"tc_rank": 126, "crash_count": 6, "startup_percent": 1.0, "bugs": [], "estimated_user_count": 1}, "js::jit::IonBuilder::jsop_initelem_array": {"tc_rank": 102, "crash_count": 7, "startup_percent": 1.0, "bugs": [], "estimated_user_count": 2}, "OOM | large | NS_ABORT_OOM | nsTArray_base<T>::EnsureCapacity<T> | gfxPrefs::PrefTemplate<T>::PrefTemplate": {"tc_rank": 10, "crash_count": 24, "startup_percent": 1.0, "bugs": [], "estimated_user_count": 2}, "js::jit::PropertyReadIsIdempotent": {"tc_rank": 79, "crash_count": 8, "startup_percent": 1.0, "bugs": [], "estimated_user_count": 1}, "style::properties::{{impl}}::clone": {"tc_rank": 23, "crash_count": 17, "startup_percent": 1.0, "bugs": [], "estimated_user_count": 1}, "nsTArray_Impl<T>::Compare<T> | mozilla::Preferences::InitInitialObjects": {"tc_rank": 173, "crash_count": 5, "startup_percent": 1.0, "bugs": [], "estimated_user_count": 1}, "sqlite3VdbeHalt": {"tc_rank": 66, "crash_count": 9, "startup_percent": 1.0, "bugs": [{"resolution": "WORKSFORME", "cf_status_firefox67": "---", "id": 695893, "cf_tracking_firefox67": "---", "cf_status_firefox68": "---", "last_change_time": "2014-09-04T13:04:12Z"}], "estimated_user_count": 1}, "style::stylesheets::stylesheet::StylesheetContents::from_str": {"tc_rank": 127, "crash_count": 6, "startup_percent": 1.0, "bugs": [], "estimated_user_count": 1}, "NS_InvokeByIndex": {"tc_rank": 174, "crash_count": 5, "startup_percent": 1.0, "bugs": [{"resolution": "WORKSFORME", "cf_status_firefox67": "---", "id": 1038927, "cf_tracking_firefox67": "---", "cf_status_firefox68": "---", "last_change_time": "2014-10-30T21:37:36Z"}], "estimated_user_count": 1}, "js::NewDtoaState": {"tc_rank": 175, "crash_count": 5, "startup_percent": 1.0, "bugs": [], "estimated_user_count": 1}, "js::PrivateScriptData::XDR<T>": {"tc_rank": 80, "crash_count": 8, "startup_percent": 1.0, "bugs": [], "estimated_user_count": 7}, "nsInputStreamPump::Create": {"tc_rank": 103, "crash_count": 7, "startup_percent": 1.0, "bugs": [], "estimated_user_count": 1}, "js::ctypes::Int64::ToString": {"tc_rank": 67, "crash_count": 9, "startup_percent": 1.0, "bugs": [], "estimated_user_count": 1}, "js::NewObjectWithGivenTaggedProto": {"tc_rank": 81, "crash_count": 8, "startup_percent": 1.0, "bugs": [], "estimated_user_count": 2}, "icu_63::number::impl::Grouper::getPrimary": {"tc_rank": 82, "crash_count": 8, "startup_percent": 1.0, "bugs": [], "estimated_user_count": 2}, "js::jit::IonBuilder::makeCallHelper": {"tc_rank": 49, "crash_count": 10, "startup_percent": 1.0, "bugs": [], "estimated_user_count": 1}, "mozilla::dom::Element::WrapObject": {"tc_rank": 83, "crash_count": 8, "startup_percent": 1.0, "bugs": [{"resolution": "", "cf_status_firefox67": "---", "id": 1286756, "cf_tracking_firefox67": "---", "cf_status_firefox68": "---", "last_change_time": "2019-03-13T13:42:05Z"}], "estimated_user_count": 1}, "js::GenericCreatePrototype<T>": {"tc_rank": 50, "crash_count": 10, "startup_percent": 1.0, "bugs": [], "estimated_user_count": 1}, "js::InternalBarrierMethods<T>::preBarrier": {"tc_rank": 176, "crash_count": 5, "startup_percent": 1.0, "bugs": [], "estimated_user_count": 1}, "BasedArrayPtr<T>::GetCheckedPtr": {"tc_rank": 128, "crash_count": 6, "startup_percent": 1.0, "bugs": [], "estimated_user_count": 1}, "mozilla::gfx::VRSystemManagerExternal::Create": {"tc_rank": 177, "crash_count": 5, "startup_percent": 1.0, "bugs": [], "estimated_user_count": 2}, "js::jit::CacheIRCompiler::emitLoadNewObjectFromTemplateResult": {"tc_rank": 39, "crash_count": 12, "startup_percent": 1.0, "bugs": [], "estimated_user_count": 1}, "nsNodeUtils::AttributeWillChange": {"tc_rank": 51, "crash_count": 10, "startup_percent": 1.0, "bugs": [{"resolution": "INCOMPLETE", "cf_status_firefox67": "---", "id": 1302319, "cf_tracking_firefox67": "---", "cf_status_firefox68": "---", "last_change_time": "2017-04-25T16:48:35Z"}], "estimated_user_count": 2}, "js::detail::OrderedHashTable<T>::Range::rekeyFront": {"tc_rank": 129, "crash_count": 6, "startup_percent": 1.0, "bugs": [], "estimated_user_count": 1}, "mozilla::layers::AsyncPanZoomController::CalculatePendingDisplayPort": {"tc_rank": 178, "crash_count": 5, "startup_percent": 1.0, "bugs": [], "estimated_user_count": 1}, "nsLookAndFeel::nsLookAndFeel": {"tc_rank": 36, "crash_count": 13, "startup_percent": 1.0, "bugs": [], "estimated_user_count": 2}, "mozilla::net::nsStandardURL::nsStandardURL": {"tc_rank": 20, "crash_count": 18, "startup_percent": 1.0, "bugs": [], "estimated_user_count": 1}, "nsStringBundleService::nsStringBundleService": {"tc_rank": 52, "crash_count": 10, "startup_percent": 1.0, "bugs": [], "estimated_user_count": 1}, "core::result::Result<T>, style::properties::CSSWideKeyword, >": {"tc_rank": 84, "crash_count": 8, "startup_percent": 1.0, "bugs": [], "estimated_user_count": 1}, "js::ToPropertyDescriptor": {"tc_rank": 24, "crash_count": 17, "startup_percent": 1.0, "bugs": [], "estimated_user_count": 2}, "nsLocalFile::AppendRelativePath": {"tc_rank": 68, "crash_count": 9, "startup_percent": 1.0, "bugs": [], "estimated_user_count": 1}, "style::values::specified::image::{{impl}}::parse": {"tc_rank": 13, "crash_count": 23, "startup_percent": 1.0, "bugs": [{"resolution": "", "cf_status_firefox67": "---", "id": 1426681, "cf_tracking_firefox67": "---", "cf_status_firefox68": "---", "last_change_time": "2018-06-25T01:18:56Z"}], "estimated_user_count": 3}, "mozilla::dom::Element::BindToTree": {"tc_rank": 130, "crash_count": 6, "startup_percent": 1.0, "bugs": [], "estimated_user_count": 1}, "EMPTY: no crashing thread identified; ERROR_NO_MINIDUMP_HEADER": {"tc_rank": 2, "crash_count": 77, "startup_percent": 1.0, "bugs": [{"resolution": "", "id": 610551, "last_change_time": "2019-01-06T00:53:22Z"}, {"resolution": "WONTFIX", "cf_status_firefox67": "---", "id": 711568, "cf_tracking_firefox67": "---", "cf_status_firefox68": "---", "last_change_time": "2017-05-16T14:24:21Z"}, {"resolution": "INCOMPLETE", "cf_status_firefox67": "---", "id": 837835, "cf_tracking_firefox67": "---", "cf_status_firefox68": "---", "last_change_time": "2018-12-05T15:22:51Z"}, {"resolution": "WORKSFORME", "cf_status_firefox67": "---", "id": 945328, "cf_tracking_firefox67": "---", "cf_status_firefox68": "---", "last_change_time": "2014-01-16T21:07:59Z"}, {"resolution": "", "cf_status_firefox67": "---", "id": 1245570, "cf_tracking_firefox67": "---", "cf_status_firefox68": "---", "last_change_time": "2018-08-08T02:39:45Z"}, {"resolution": "FIXED", "cf_status_firefox67": "---", "id": 1255050, "cf_tracking_firefox67": "---", "cf_status_firefox68": "---", "last_change_time": "2016-03-23T23:39:32Z"}, {"resolution": "", "cf_status_firefox67": "---", "id": 1360392, "cf_tracking_firefox67": "---", "cf_status_firefox68": "---", "last_change_time": "2018-09-11T15:19:21Z"}, {"resolution": "", "id": 1290884, "last_change_time": "2018-10-05T00:05:04Z"}], "estimated_user_count": 32}, "net_IsAbsoluteURL": {"tc_rank": 179, "crash_count": 5, "startup_percent": 1.0, "bugs": [], "estimated_user_count": 1}, "mozilla::dom::quota::QuotaManager::IsRunningGTests": {"tc_rank": 53, "crash_count": 10, "startup_percent": 1.0, "bugs": [], "estimated_user_count": 1}, "DoCheckLoadURIChecks": {"tc_rank": 196, "crash_count": 5, "startup_percent": 1.0, "bugs": [], "estimated_user_count": 1}, "gfxPrefs::gfxPrefs": {"tc_rank": 104, "crash_count": 7, "startup_percent": 1.0, "bugs": [], "estimated_user_count": 2}, "nsContentUtils::HasMutationListeners": {"tc_rank": 180, "crash_count": 5, "startup_percent": 1.0, "bugs": [], "estimated_user_count": 1}, "TimerThread::RemoveLeadingCanceledTimersInternal": {"tc_rank": 131, "crash_count": 6, "startup_percent": 1.0, "bugs": [], "estimated_user_count": 1}, "js::ScriptSourceObject::initElementProperties": {"tc_rank": 29, "crash_count": 15, "startup_percent": 1.0, "bugs": [], "estimated_user_count": 1}, "DefineSubcomponentProperty": {"tc_rank": 193, "crash_count": 5, "startup_percent": 1.0, "bugs": [], "estimated_user_count": 2}, "js::jit::StrictlyEqual<T>": {"tc_rank": 86, "crash_count": 8, "startup_percent": 1.0, "bugs": [], "estimated_user_count": 1}, "xul.dll | nsMaybeWeakPtrArray<T>::AppendWeakElement": {"tc_rank": 40, "crash_count": 12, "startup_percent": 1.0, "bugs": [], "estimated_user_count": 1}, "mozilla::dom::ServiceWorkerRegistrar::GetShutdownPhase": {"tc_rank": 1, "crash_count": 370, "startup_percent": 1.0, "bugs": [{"resolution": "", "cf_status_firefox67": "affected", "id": 1403348, "cf_tracking_firefox67": "---", "cf_status_firefox68": "---", "last_change_time": "2019-03-13T18:22:36Z"}], "estimated_user_count": 60}, "nsCOMPtr_base::assign_from_gs_contractid | AddAppDirToCommandLine": {"tc_rank": 181, "crash_count": 5, "startup_percent": 1.0, "bugs": [], "estimated_user_count": 1}, "Gecko_GetBeforeOrAfterPseudo": {"tc_rank": 182, "crash_count": 5, "startup_percent": 1.0, "bugs": [], "estimated_user_count": 1}, "mozilla::dom::MessageListenerManager_Binding::addMessageListener": {"tc_rank": 183, "crash_count": 5, "startup_percent": 1.0, "bugs": [], "estimated_user_count": 1}, "nsContentUtils::GetUTFOrigin": {"tc_rank": 132, "crash_count": 6, "startup_percent": 1.0, "bugs": [], "estimated_user_count": 1}, "xul.dll | nsObserverService::AddObserver": {"tc_rank": 37, "crash_count": 13, "startup_percent": 1.0, "bugs": [], "estimated_user_count": 2}, "NS_InitXPCOM": {"tc_rank": 26, "crash_count": 16, "startup_percent": 1.0, "bugs": [], "estimated_user_count": 9}, "js::detail::BumpChunk::~BumpChunk": {"tc_rank": 41, "crash_count": 12, "startup_percent": 1.0, "bugs": [], "estimated_user_count": 2}, "LdrpWriteBackProtectedDelayLoad": {"tc_rank": 9, "crash_count": 31, "startup_percent": 1.0, "bugs": [], "estimated_user_count": 28}, "vcruntime140.dll | mozilla::FileLocation::Data::Copy": {"tc_rank": 69, "crash_count": 9, "startup_percent": 1.0, "bugs": [], "estimated_user_count": 3}, "mozilla::Preferences::AddBoolVarCache": {"tc_rank": 6, "crash_count": 48, "startup_percent": 1.0, "bugs": [{"resolution": "", "cf_status_firefox67": "affected", "id": 1276488, "cf_tracking_firefox67": "---", "cf_status_firefox68": "?", "last_change_time": "2019-03-19T20:34:31Z"}], "estimated_user_count": 12}, "nsMediaFeatures::InitSystemMetrics": {"tc_rank": 105, "crash_count": 7, "startup_percent": 1.0, "bugs": [], "estimated_user_count": 1}, "mozilla::dom::WebExtensionPolicy_Binding::get_id": {"tc_rank": 70, "crash_count": 9, "startup_percent": 1.0, "bugs": [], "estimated_user_count": 2}, "nsWidgetWindowsModuleDtor": {"tc_rank": 7, "crash_count": 36, "startup_percent": 1.0, "bugs": [], "estimated_user_count": 10}, "memcmp | _Wcsftime_l": {"tc_rank": 133, "crash_count": 6, "startup_percent": 1.0, "bugs": [], "estimated_user_count": 2}, "nsWindow::DispatchFocusToTopLevelWindow": {"tc_rank": 21, "crash_count": 18, "startup_percent": 1.0, "bugs": [], "estimated_user_count": 1}, "Interpret": {"tc_rank": 134, "crash_count": 6, "startup_percent": 1.0, "bugs": [{"resolution": "", "cf_status_firefox67": "---", "id": 682573, "cf_tracking_firefox67": "---", "cf_status_firefox68": "---", "last_change_time": "2014-07-24T18:07:35Z"}, {"resolution": "FIXED", "cf_status_firefox67": "---", "id": 884194, "cf_tracking_firefox67": "---", "cf_status_firefox68": "---", "last_change_time": "2013-09-18T16:00:15Z"}, {"resolution": "FIXED", "cf_status_firefox67": "---", "id": 917792, "cf_tracking_firefox67": "---", "cf_status_firefox68": "---", "last_change_time": "2013-10-08T22:01:56Z"}, {"resolution": "FIXED", "cf_status_firefox67": "---", "id": 935348, "cf_tracking_firefox67": "---", "cf_status_firefox68": "---", "last_change_time": "2013-11-13T00:31:27Z"}, {"resolution": "WORKSFORME", "cf_status_firefox67": "---", "id": 937914, "cf_tracking_firefox67": "---", "cf_status_firefox68": "---", "last_change_time": "2019-03-13T13:42:05Z"}, {"resolution": "FIXED", "cf_status_firefox67": "---", "id": 1185961, "cf_tracking_firefox67": "---", "cf_status_firefox68": "---", "last_change_time": "2015-08-26T18:40:33Z"}, {"resolution": "", "cf_status_firefox67": "---", "id": 1260683, "cf_tracking_firefox67": "---", "cf_status_firefox68": "---", "last_change_time": "2017-04-04T20:16:43Z"}, {"resolution": "FIXED", "cf_status_firefox67": "---", "id": 961969, "cf_tracking_firefox67": "---", "cf_status_firefox68": "---", "last_change_time": "2015-09-09T02:26:29Z"}], "estimated_user_count": 6}, "js::jit::AssemblerX86Shared::andl": {"tc_rank": 87, "crash_count": 8, "startup_percent": 1.0, "bugs": [], "estimated_user_count": 1}, "mozilla::URLPreloader::BackgroundReadFiles": {"tc_rank": 4, "crash_count": 61, "startup_percent": 1.0, "bugs": [{"resolution": "INCOMPLETE", "cf_status_firefox67": "---", "id": 1458782, "cf_tracking_firefox67": "---", "cf_status_firefox68": "---", "last_change_time": "2018-05-07T20:42:52Z"}], "estimated_user_count": 33}, "nsTArray_Impl<T>::Compare<T> | NS_QuickSort": {"tc_rank": 184, "crash_count": 5, "startup_percent": 1.0, "bugs": [], "estimated_user_count": 2}, "TimerThread::Run": {"tc_rank": 101, "crash_count": 7, "startup_percent": 1.0, "bugs": [{"resolution": "", "id": 504669, "last_change_time": "2018-11-24T17:30:03Z"}, {"resolution": "", "cf_status_firefox67": "---", "id": 657962, "cf_tracking_firefox67": "---", "cf_status_firefox68": "---", "last_change_time": "2019-04-10T22:03:22Z"}, {"resolution": "", "cf_status_firefox67": "---", "id": 1334383, "cf_tracking_firefox67": "---", "cf_status_firefox68": "---", "last_change_time": "2019-04-08T06:02:42Z"}, {"resolution": "INCOMPLETE", "cf_status_firefox67": "---", "id": 1402169, "cf_tracking_firefox67": "---", "cf_status_firefox68": "---", "last_change_time": "2017-10-16T07:20:41Z"}, {"resolution": "INCOMPLETE", "cf_status_firefox67": "---", "id": 1414488, "cf_tracking_firefox67": "---", "cf_status_firefox68": "---", "last_change_time": "2017-11-27T07:56:49Z"}, {"resolution": "INCOMPLETE", "cf_status_firefox67": "---", "id": 1416590, "cf_tracking_firefox67": "---", "cf_status_firefox68": "---", "last_change_time": "2017-12-18T08:57:20Z"}, {"resolution": "", "cf_status_firefox67": "---", "id": 1426991, "cf_tracking_firefox67": "---", "cf_status_firefox68": "---", "last_change_time": "2019-04-08T22:27:48Z"}, {"resolution": "INCOMPLETE", "cf_status_firefox67": "---", "id": 1430528, "cf_tracking_firefox67": "---", "cf_status_firefox68": "---", "last_change_time": "2019-03-13T13:42:05Z"}, {"resolution": "INCOMPLETE", "cf_status_firefox67": "---", "id": 1434510, "cf_tracking_firefox67": "---", "cf_status_firefox68": "---", "last_change_time": "2019-03-13T13:42:05Z"}], "estimated_user_count": 1}, "js::irregexp::RegExpParser<T>::ParseDisjunction": {"tc_rank": 185, "crash_count": 5, "startup_percent": 1.0, "bugs": [], "estimated_user_count": 1}, "js::jit::MacroAssemblerX64::unboxGCThingForPreBarrierTrampoline": {"tc_rank": 89, "crash_count": 8, "startup_percent": 1.0, "bugs": [], "estimated_user_count": 1}, "offsetTOCLookupFn": {"tc_rank": 186, "crash_count": 5, "startup_percent": 1.0, "bugs": [], "estimated_user_count": 2}, "nsCSSFrameConstructor::ContentRangeInserted": {"tc_rank": 187, "crash_count": 5, "startup_percent": 1.0, "bugs": [{"resolution": "", "cf_status_firefox67": "---", "id": 1359232, "cf_tracking_firefox67": "---", "cf_status_firefox68": "---", "last_change_time": "2019-02-11T06:40:56Z"}], "estimated_user_count": 1}, "nsSystemInfo::Init": {"tc_rank": 135, "crash_count": 6, "startup_percent": 1.0, "bugs": [], "estimated_user_count": 1}, "js::jit::IonBuilder::initializeArrayElement": {"tc_rank": 136, "crash_count": 6, "startup_percent": 1.0, "bugs": [], "estimated_user_count": 1}, "memcpy | nsZipCursor::ReadOrCopy": {"tc_rank": 11, "crash_count": 24, "startup_percent": 1.0, "bugs": [], "estimated_user_count": 4}, "nsPrefBranch::NotifyObserver": {"tc_rank": 188, "crash_count": 5, "startup_percent": 1.0, "bugs": [{"resolution": "WORKSFORME", "cf_status_firefox67": "---", "id": 614082, "cf_tracking_firefox67": "---", "cf_status_firefox68": "---", "last_change_time": "2018-02-02T02:26:55Z"}], "estimated_user_count": 2}, "js::TypeMonitorResult": {"tc_rank": 54, "crash_count": 10, "startup_percent": 1.0, "bugs": [{"resolution": "", "cf_status_firefox67": "---", "id": 1180989, "cf_tracking_firefox67": "---", "cf_status_firefox68": "---", "last_change_time": "2016-10-05T14:42:31Z"}, {"resolution": "FIXED", "cf_status_firefox67": "---", "id": 1291685, "cf_tracking_firefox67": "---", "cf_status_firefox68": "---", "last_change_time": "2016-11-18T02:37:46Z"}, {"resolution": "FIXED", "cf_status_firefox67": "---", "id": 1264429, "cf_tracking_firefox67": "---", "cf_status_firefox68": "---", "last_change_time": "2016-04-18T08:39:18Z"}], "estimated_user_count": 1}, "mozilla::dom::NodeInfo::NodeInfo": {"tc_rank": 88, "crash_count": 8, "startup_percent": 1.0, "bugs": [], "estimated_user_count": 1}, "mozilla::dom::Document::BlockOnload": {"tc_rank": 189, "crash_count": 5, "startup_percent": 1.0, "bugs": [], "estimated_user_count": 1}, "nsJARInputStream::Read": {"tc_rank": 137, "crash_count": 6, "startup_percent": 1.0, "bugs": [], "estimated_user_count": 0}, "mozilla::xpcom::StaticComponents::LookupByContractID": {"tc_rank": 106, "crash_count": 7, "startup_percent": 1.0, "bugs": [], "estimated_user_count": 1}, "nsXPConnect::InitStatics": {"tc_rank": 5, "crash_count": 50, "startup_percent": 1.0, "bugs": [{"resolution": "", "cf_status_firefox67": "---", "id": 1326539, "cf_tracking_firefox67": "---", "cf_status_firefox68": "---", "last_change_time": "2018-10-25T13:48:52Z"}], "estimated_user_count": 23}, "PLDHashTable::HashVoidPtrKeyStub | PLDHashTable::Add | nsMemoryReporterManager::RegisterReporterHelper": {"tc_rank": 17, "crash_count": 19, "startup_percent": 1.0, "bugs": [], "estimated_user_count": 2}, "nsTArray_base<T>::EnsureCapacity<T> | nsTArray_base<T>::SwapArrayElements<T> | nsComputedDOMStyle::RegisterPrefChangeCallbacks": {"tc_rank": 190, "crash_count": 5, "startup_percent": 1.0, "bugs": [], "estimated_user_count": 1}, "mozilla::ClearOnShutdown<T>": {"tc_rank": 191, "crash_count": 5, "startup_percent": 1.0, "bugs": [], "estimated_user_count": 1}, "_com_error::_com_error": {"tc_rank": 107, "crash_count": 7, "startup_percent": 1.0, "bugs": [], "estimated_user_count": 1}, "mozilla::dom::Document::FlushPendingNotifications": {"tc_rank": 192, "crash_count": 5, "startup_percent": 1.0, "bugs": [], "estimated_user_count": 2}, "JS::Compartment::wrap": {"tc_rank": 167, "crash_count": 5, "startup_percent": 1.0, "bugs": [], "estimated_user_count": 1}, "nsScriptSecurityManager::JSPrincipalsSubsume": {"tc_rank": 194, "crash_count": 5, "startup_percent": 1.0, "bugs": [], "estimated_user_count": 1}, "strlen | PropertySpecNameToId": {"tc_rank": 90, "crash_count": 8, "startup_percent": 1.0, "bugs": [], "estimated_user_count": 1}, "mozilla::dom::FallbackEncoding::~FallbackEncoding": {"tc_rank": 195, "crash_count": 5, "startup_percent": 1.0, "bugs": [], "estimated_user_count": 1}, "style::custom_properties::parse_self_contained_declaration_value": {"tc_rank": 138, "crash_count": 6, "startup_percent": 1.0, "bugs": [], "estimated_user_count": 1}, "nsComponentManagerImpl::RegisterModule": {"tc_rank": 22, "crash_count": 18, "startup_percent": 1.0, "bugs": [{"resolution": "", "cf_status_firefox67": "---", "id": 1105233, "cf_tracking_firefox67": "---", "cf_status_firefox68": "---", "last_change_time": "2019-01-07T11:06:38Z"}, {"resolution": "WORKSFORME", "id": 1222014, "last_change_time": "2016-07-21T16:28:31Z"}], "estimated_user_count": 4}, "PR_Connect | mozilla::net::NewTCPSocketPair": {"tc_rank": 55, "crash_count": 10, "startup_percent": 1.0, "bugs": [], "estimated_user_count": 1}, "js::gc::AtomMarkingRuntime::markAtom<T>": {"tc_rank": 85, "crash_count": 8, "startup_percent": 1.0, "bugs": [{"resolution": "FIXED", "cf_status_firefox67": "---", "id": 1384544, "cf_tracking_firefox67": "---", "cf_status_firefox68": "---", "last_change_time": "2018-11-05T22:10:08Z"}, {"resolution": "", "cf_status_firefox67": "---", "id": 1436984, "cf_tracking_firefox67": "---", "cf_status_firefox68": "---", "last_change_time": "2018-09-28T15:02:55Z"}], "estimated_user_count": 2}, "memcpy | nsJARInputStream::Read": {"tc_rank": 139, "crash_count": 6, "startup_percent": 1.0, "bugs": [], "estimated_user_count": 5}, "mozilla::detail::HashTable<T>::changeTableSize | mozilla::detail::HashTable<T>::add<T> | mozilla::detail::HashTable<T>::relookupOrAdd<T> | js::ObjectGroup::newArrayObject": {"tc_rank": 42, "crash_count": 12, "startup_percent": 1.0, "bugs": [], "estimated_user_count": 2}, "mozilla::dom::Node_Binding::get_nodePrincipal": {"tc_rank": 197, "crash_count": 5, "startup_percent": 1.0, "bugs": [], "estimated_user_count": 1}, "ogg_set_mem_functions": {"tc_rank": 198, "crash_count": 5, "startup_percent": 1.0, "bugs": [], "estimated_user_count": 1}, "StringBuilder::OnCharacterSourceShift": {"tc_rank": 199, "crash_count": 5, "startup_percent": 1.0, "bugs": [], "estimated_user_count": 1}, "js::frontend::FoldConstants": {"tc_rank": 108, "crash_count": 7, "startup_percent": 1.0, "bugs": [{"resolution": "WORKSFORME", "cf_status_firefox67": "---", "id": 810659, "cf_tracking_firefox67": "---", "cf_status_firefox68": "---", "last_change_time": "2016-08-16T13:21:23Z"}], "estimated_user_count": 2}, "CrashReporter::OOPInit": {"tc_rank": 8, "crash_count": 36, "startup_percent": 1.0, "bugs": [{"resolution": "", "cf_status_firefox67": "---", "id": 1347867, "cf_tracking_firefox67": "---", "cf_status_firefox68": "---", "last_change_time": "2018-11-19T20:00:01Z"}], "estimated_user_count": 7}, "nsPropertyElement::QueryInterface": {"tc_rank": 109, "crash_count": 7, "startup_percent": 1.0, "bugs": [], "estimated_user_count": 1}, "js::jit::MTableSwitch::getSuccessor": {"tc_rank": 25, "crash_count": 17, "startup_percent": 1.0, "bugs": [], "estimated_user_count": 1}, "nsTArray_Impl<T>::RemoveElementsAt | mozilla::dom::Document::EndUpdate": {"tc_rank": 200, "crash_count": 5, "startup_percent": 1.0, "bugs": [], "estimated_user_count": 1}}}